odoo/addons/product_code_mandatory/README.rst
odoo/addons/product_code_mandatory/__init__.py
odoo/addons/product_code_mandatory/__manifest__.py
odoo/addons/product_code_mandatory/data/product_code_seq.xml
odoo/addons/product_code_mandatory/i18n/ca.po
odoo/addons/product_code_mandatory/i18n/fr.po
odoo/addons/product_code_mandatory/i18n/fr_FR.po
odoo/addons/product_code_mandatory/i18n/it.po
odoo/addons/product_code_mandatory/i18n/product_code_mandatory.pot
odoo/addons/product_code_mandatory/i18n/pt.po
odoo/addons/product_code_mandatory/models/__init__.py
odoo/addons/product_code_mandatory/models/product.py
odoo/addons/product_code_mandatory/readme/CONTRIBUTORS.md
odoo/addons/product_code_mandatory/readme/DESCRIPTION.md
odoo/addons/product_code_mandatory/readme/USAGE.md
odoo/addons/product_code_mandatory/static/description/icon.png
odoo/addons/product_code_mandatory/static/description/index.html
odoo/addons/product_code_mandatory/tests/__init__.py
odoo/addons/product_code_mandatory/tests/test_product_code.py
odoo/addons/product_code_mandatory/views/product_view.xml
odoo_addon_product_code_mandatory-17.0.1.0.0.4.dist-info/METADATA
odoo_addon_product_code_mandatory-17.0.1.0.0.4.dist-info/WHEEL
odoo_addon_product_code_mandatory-17.0.1.0.0.4.dist-info/top_level.txt
odoo_addon_product_code_mandatory-17.0.1.0.0.4.dist-info/RECORD
